pytweetdeck/__init__.py
pytweetdeck/api.py
pytweetdeck-1.0.1.dist-info/LICENSE
pytweetdeck-1.0.1.dist-info/METADATA
pytweetdeck-1.0.1.dist-info/WHEEL
pytweetdeck-1.0.1.dist-info/top_level.txt
pytweetdeck-1.0.1.dist-info/RECORD
