Metadata-Version: 2.1
Name: pytweetdeck
Version: 1.0.1
Summary: Wrapper library of TweetDeck's internal api.
Home-page: https://github.com/m4fn3/pytweetdeck
Author: mafu
Author-email: mafusukee@gmail.com
License: UNKNOWN
Platform: UNKNOWN
Classifier: Programming Language :: Python :: 3
Classifier: License :: OSI Approved :: MIT License
Classifier: Operating System :: OS Independent
License-File: LICENSE
Requires-Dist: requests
Requires-Dist: lxml
